{
  "kind": "coverage_report",
  "version": "1.0",
  "generatedAt": "2026-02-23T23:04:24.215Z",
  "sources": {
    "buildRequest": true,
    "implementationPlan": true
  },
  "requirements": {
    "total": 1,
    "implemented": 1,
    "items": [
      {
        "id": "REQ-5",
        "summary": "Change the Pro upgrade call-to-action text from 'Please log in to upgrade' to 'Pay $20 to upgrade'",
        "status": "implemented",
        "plannedFiles": [
          "frontend/src/components/ProFeaturesModal.tsx",
          "frontend/src/components/ProUpgrade.tsx"
        ],
        "matchedFiles": [
          "frontend/src/components/ProFeaturesModal.tsx",
          "frontend/src/components/ProUpgrade.tsx"
        ]
      }
    ]
  },
  "changedFiles": [
    "build-request.json",
    "feature_evidence.json",
    "frontend-file-summaries.txt",
    "frontend-implementation-plan.json",
    "frontend/src/components/ProFeaturesModal.tsx",
    "frontend/src/components/ProUpgrade.tsx",
    "project_state.json",
    "scratch/component-selection.json",
    "spec.md",
    "spec_vs_diff_report.json"
  ]
}