{
  "schemaVersion": "1.0.0",
  "projectStateVersion": 3,
  "summary": "App with Pro features: free for the owner's account, costs $20 for other users",
  "architectural_notes": [
    "Pro feature access controlled by Internet Identity",
    "Payment system for $20 Pro upgrade for non-owner accounts"
  ],
  "known_issues": [],
  "isFixRequest": false,
  "existing_features": [
    {
      "id": "feature-update-frontend-pro-upgrade-ui-to-reflect-that-the-owner-has-free-pro-access-automatically",
      "title": "Update frontend Pro upgrade UI to reflect that the owner has free Pro access automatically",
      "reqIds": [
        "REQ-3"
      ],
      "version": 1
    },
    {
      "id": "feature-display-20-to-upgrade-messaging-in-profeaturesmodal-for-non-owner-accounts",
      "title": "Display '$20 to upgrade' messaging in ProFeaturesModal for non-owner accounts",
      "reqIds": [
        "REQ-4"
      ],
      "version": 1
    }
  ],
  "new_feature_requests": [
    {
      "id": "AR-1",
      "summary": "Pro badge with popup showing features and $20 upgrade option",
      "reqIds": [],
      "status": "pending"
    },
    {
      "id": "AR-2",
      "summary": "Free Pro access for owner's Internet Identity account",
      "reqIds": [],
      "status": "pending"
    },
    {
      "id": "AR-3",
      "summary": "$20 payment requirement for Pro features for all other users",
      "reqIds": [],
      "status": "pending"
    },
    {
      "id": "AR-4",
      "summary": "Implement backend logic to automatically grant Pro subscription status to the owner's Internet Identity account without payment",
      "reqIds": [
        "REQ-1"
      ],
      "status": "pending"
    },
    {
      "id": "AR-5",
      "summary": "Ensure all other user accounts require a $20 USD payment to access Pro features",
      "reqIds": [
        "REQ-2"
      ],
      "status": "pending"
    }
  ],
  "projectName": "Nexora AI",
  "clarification_mode": "instant",
  "clarification_rounds": 0
}